chainlink-wrapper/__init__.py
chainlink-wrapper/wrapper.py
chainlink_wrapper/__init__.py
chainlink_wrapper/wrapper.py
drachma_chainlink_wrapper-1.0.1.dist-info/METADATA
drachma_chainlink_wrapper-1.0.1.dist-info/WHEEL
drachma_chainlink_wrapper-1.0.1.dist-info/top_level.txt
drachma_chainlink_wrapper-1.0.1.dist-info/RECORD
