Metadata-Version: 2.1
Name: drachma-chainlink-wrapper
Version: 1.0.1
Summary: A wrapper to get live price data from chainlink oracles on-chain
Home-page: https://github.com/Drachma-Capital/drachma-chainlink-wrapper
Author: Joshua Finkelstein
Author-email: joshfinkelstein3@gmail.com
License: BSD 2-clause
Classifier: Development Status :: 1 - Planning
Classifier: Intended Audience :: Science/Research
Classifier: License :: OSI Approved :: BSD License
Classifier: Operating System :: POSIX :: Linux
Classifier: Programming Language :: Python :: 2
Classifier: Programming Language :: Python :: 2.7
Classifier: Programming Language :: Python :: 3
Classifier: Programming Language :: Python :: 3.4
Classifier: Programming Language :: Python :: 3.5
Requires-Dist: web3
